fishtools/__init__.py
fishtools/cli.py
fishtools/config.py
fishtools/data.py
fishtools/probes.py
fishtools/process.py
fishtools/segment.py
fishtools/utils.py
fishtools/vis.py
fishtools-0.1.2.dist-info/entry_points.txt
fishtools-0.1.2.dist-info/LICENSE
fishtools-0.1.2.dist-info/WHEEL
fishtools-0.1.2.dist-info/METADATA
fishtools-0.1.2.dist-info/RECORD
