Metadata-Version: 2.1
Name: fishtools
Version: 0.1.2
Summary: Tools for analysing FISH data.
Author: Matthew Hartley
Author-email: mhartley@cantab.net
Requires-Python: >=3.7,<4.0
Classifier: Programming Language :: Python :: 3
Classifier: Programming Language :: Python :: 3.7
Classifier: Programming Language :: Python :: 3.8
Requires-Dist: dtoolbioimage (>=0.1.9,<0.2.0)
Requires-Dist: pandas (>=1.0.5,<2.0.0)
Requires-Dist: parse (>=1.16.0,<2.0.0)
Requires-Dist: ruamel.yaml (>=0.16.10,<0.17.0)
